fcd/ChemNet_v0.13_pretrained.pt
fcd/__init__.py
fcd/fcd.py
fcd/torch_layers.py
fcd/utils.py
fcd-1.2.2.dist-info/METADATA
fcd-1.2.2.dist-info/WHEEL
fcd-1.2.2.dist-info/licenses/LICENSE
fcd-1.2.2.dist-info/RECORD
