Metadata-Version: 2.3
Name: fcd
Version: 1.2.2
Summary: Fréchet ChEMNet Distance
Project-URL: Homepage, https://github.com/bioinf-jku/FCD
Project-URL: Documentation, https://github.com/bioinf-jku/FCD
Project-URL: Repository, https://github.com/bioinf-jku/FCD
Author-email: Philipp Renz <renz.ph@gmail.com>
License:                    GNU LESSER GENERAL PUBLIC LICENSE
License-File: LICENSE
Keywords: cheminformatics,deep learning,generative models,machine learning
Classifier: Development Status :: 5 - Production/Stable
Classifier: Programming Language :: Python :: 3
Requires-Python: >=3.8
Requires-Dist: numpy
Requires-Dist: rdkit
Requires-Dist: scipy
Requires-Dist: torch
